LICENSE.txt
MANIFEST.in
README.md
requirements.txt
setup.py
UnifiedLog/Lib.py
UnifiedLog/__init__.py
UnifiedLog/data_format.py
UnifiedLog/dsc_file.py
UnifiedLog/logger.py
UnifiedLog/resources.py
UnifiedLog/tracev3_file.py
UnifiedLog/uuidtext_file.py
UnifiedLog/virtual_file.py
UnifiedLog/virtual_file_system.py
UnifiedLog.egg-info/PKG-INFO
UnifiedLog.egg-info/SOURCES.txt
UnifiedLog.egg-info/dependency_links.txt
UnifiedLog.egg-info/requires.txt
UnifiedLog.egg-info/top_level.txt
scripts/UnifiedLogReader.py
scripts/tracev3_decompress.py
test_data/0000000000000030.tracev3
test_data/7EF56328D53A78B59CCCE3E3189F57
test_data/8E21CAB1DCF936B49F85CF860E6F34EC
tests/__init__.py
tests/data_format.py
tests/dsc_file.py
tests/resources.py
tests/test_lib.py
tests/tracev3_file.py
tests/uuidtext_file.py
tests/virtual_file.py
tests/virtual_file_system.py