Metadata-Version: 1.2
Name: UnifiedLog
Version: 0.3
Summary: A parser for Unified logging .tracev3 files.
Home-page: https://github.com/ydkhatri/UnifiedLogReader
Maintainer: Yogesh Khatri
Maintainer-email: yogesh@swiftforensics.com
License: MIT
Platform: UNKNOWN
Classifier: Development Status :: 3 - Alpha
Classifier: Environment :: Console
Classifier: License :: OSI Approved :: MIT License
Classifier: Operating System :: OS Independent
Classifier: Programming Language :: Python :: 3
Requires-Python: >=3.6
